instrulink/__init__.py
instrulink/bk_2555.py
instrulink/camera.py
instrulink/constants.py
instrulink/factory.py
instrulink/keysight_33500b.py
instrulink/keysight_e5061b.py
instrulink/logger.py
instrulink/nidaq.py
instrulink/oscilloscope.py
instrulink/rigol_dg1022z.py
instrulink/rigol_ds1054z.py
instrulink/si_utils.py
instrulink/sutter_mp285a.py
instrulink/utils.py
instrulink/visa_instrument.py
instrulink/waveform_generator.py
instrulink/wf_utils.py
instrulink-1.0.5.data/scripts/list_visa_resources.py
instrulink-1.0.5.data/scripts/test_33500b.py
instrulink-1.0.5.data/scripts/test_camera.py
instrulink-1.0.5.data/scripts/test_e5061b.py
instrulink-1.0.5.data/scripts/test_generator.py
instrulink-1.0.5.data/scripts/test_manipulator.py
instrulink-1.0.5.data/scripts/test_nidaq.py
instrulink-1.0.5.data/scripts/test_scope.py
instrulink-1.0.5.data/scripts/test_smoothed_waveform.py
instrulink-1.0.5.dist-info/LICENSE
instrulink-1.0.5.dist-info/METADATA
instrulink-1.0.5.dist-info/WHEEL
instrulink-1.0.5.dist-info/top_level.txt
instrulink-1.0.5.dist-info/RECORD
