Metadata-Version: 2.1
Name: instrulink
Version: 1.0.5
Summary: Python package to interface diverse laboratory instruments
Home-page: https://github.com/tjjlemaire/instrulink
Author: Theo Lemaire
Author-email: theo.lemaire1@gmail.com
License: MIT
Keywords: laboratory instrument interface python
Classifier: Development Status :: 4 - Beta
Classifier: Intended Audience :: Science/Research
Classifier: Programming Language :: Python :: 3
Classifier: Topic :: Scientific/Engineering :: Physics
License-File: LICENSE
Requires-Dist: numpy
Requires-Dist: colorlog
Requires-Dist: pyvisa
Requires-Dist: pyserial
Requires-Dist: matplotlib
Requires-Dist: nidaqmx
Requires-Dist: seaborn
Requires-Dist: tqdm
Requires-Dist: scipy
